<?xml version="1.0" encoding="UTF-8"?>

<!-- generated on 2021-11-30 09:00:38 by Eclipse SUMO GUI Version 1.10.0
<configuration xmlns:xsi="http://www.w3.org/2001/XMLSchema-instance" xsi:noNamespaceSchemaLocation="http://sumo.dlr.de/xsd/sumoConfiguration.xsd">

    <input>
        <net-file value="C:\Users\Lenovo\Documents\GitHub\Traffic_Simulation\2X3GridNetwork\2x3net.net.xml"/>
        <route-files value="C:\Users\Lenovo\Documents\GitHub\Traffic_Simulation\2X3GridNetwork\2x3Routes.xml"/>
        <additional-files value="C:\Users\Lenovo\Documents\GitHub\Traffic_Simulation\2X3GridNetwork\additionals.xml"/>
    </input>

    <output>
        <tripinfo-output value="tripinfo.xml"/>
        <statistic-output value="statistics.xml"/>
    </output>

    <report>
        <no-step-log value="true"/>
    </report>

    <traci_server>
        <remote-port value="52108"/>
    </traci_server>

</configuration>
-->

<detector xmlns:xsi="http://www.w3.org/2001/XMLSchema-instance" xsi:noNamespaceSchemaLocation="http://sumo.dlr.de/xsd/det_e2_file.xsd">
   <interval begin="0.00" end="300.00" id="detA2A3b" sampledSeconds="6.03" nVehEntered="3" nVehLeft="3" nVehSeen="3" meanSpeed="9.45" meanTimeLoss="0.67" meanOccupancy="0.43" maxOccupancy="35.71" meanMaxJamLengthInVehicles="0.00" meanMaxJamLengthInMeters="0.00" maxJamLengthInVehicles="0" maxJamLengthInMeters="0.00" jamLengthInVehiclesSum="0" jamLengthInMetersSum="0.00" meanHaltingDuration="0.00" maxHaltingDuration="0.00" haltingDurationSum="0.00" meanIntervalHaltingDuration="0.00" maxIntervalHaltingDuration="0.00" intervalHaltingDurationSum="0.00" startedHalts="0.00" meanVehicleNumber="0.03" maxVehicleNumber="1" />
   <interval begin="300.00" end="600.00" id="detA2A3b" sampledSeconds="17.85" nVehEntered="11" nVehLeft="11" nVehSeen="11" meanSpeed="11.71" meanTimeLoss="0.27" meanOccupancy="1.64" maxOccupancy="35.71" meanMaxJamLengthInVehicles="0.00" meanMaxJamLengthInMeters="0.00" maxJamLengthInVehicles="0" maxJamLengthInMeters="0.00" jamLengthInVehiclesSum="0" jamLengthInMetersSum="0.00" meanHaltingDuration="0.00" maxHaltingDuration="0.00" haltingDurationSum="0.00" meanIntervalHaltingDuration="0.00" maxIntervalHaltingDuration="0.00" intervalHaltingDurationSum="0.00" startedHalts="0.00" meanVehicleNumber="0.10" maxVehicleNumber="2" />
   <interval begin="600.00" end="900.00" id="detA2A3b" sampledSeconds="14.27" nVehEntered="8" nVehLeft="8" nVehSeen="8" meanSpeed="10.65" meanTimeLoss="0.31" meanOccupancy="1.19" maxOccupancy="35.71" meanMaxJamLengthInVehicles="0.00" meanMaxJamLengthInMeters="0.00" maxJamLengthInVehicles="0" maxJamLengthInMeters="0.00" jamLengthInVehiclesSum="0" jamLengthInMetersSum="0.00" meanHaltingDuration="0.00" maxHaltingDuration="0.00" haltingDurationSum="0.00" meanIntervalHaltingDuration="0.00" maxIntervalHaltingDuration="0.00" intervalHaltingDurationSum="0.00" startedHalts="0.00" meanVehicleNumber="0.09" maxVehicleNumber="2" />
   <interval begin="900.00" end="1200.00" id="detA2A3b" sampledSeconds="7.77" nVehEntered="4" nVehLeft="4" nVehSeen="4" meanSpeed="9.78" meanTimeLoss="0.66" meanOccupancy="0.66" maxOccupancy="35.71" meanMaxJamLengthInVehicles="0.00" meanMaxJamLengthInMeters="0.00" maxJamLengthInVehicles="0" maxJamLengthInMeters="0.00" jamLengthInVehiclesSum="0" jamLengthInMetersSum="0.00" meanHaltingDuration="0.00" maxHaltingDuration="0.00" haltingDurationSum="0.00" meanIntervalHaltingDuration="0.00" maxIntervalHaltingDuration="0.00" intervalHaltingDurationSum="0.00" startedHalts="0.00" meanVehicleNumber="0.04" maxVehicleNumber="1" />
   <interval begin="1200.00" end="1500.00" id="detA2A3b" sampledSeconds="63.04" nVehEntered="40" nVehLeft="39" nVehSeen="40" meanSpeed="11.98" meanTimeLoss="0.19" meanOccupancy="5.61" maxOccupancy="35.71" meanMaxJamLengthInVehicles="0.00" meanMaxJamLengthInMeters="0.00" maxJamLengthInVehicles="0" maxJamLengthInMeters="0.00" jamLengthInVehiclesSum="0" jamLengthInMetersSum="0.00" meanHaltingDuration="0.00" maxHaltingDuration="0.00" haltingDurationSum="0.00" meanIntervalHaltingDuration="0.00" maxIntervalHaltingDuration="0.00" intervalHaltingDurationSum="0.00" startedHalts="0.00" meanVehicleNumber="0.35" maxVehicleNumber="2" />
   <interval begin="1500.00" end="1800.00" id="detA2A3b" sampledSeconds="139.18" nVehEntered="83" nVehLeft="83" nVehSeen="84" meanSpeed="11.33" meanTimeLoss="0.31" meanOccupancy="12.25" maxOccupancy="35.71" meanMaxJamLengthInVehicles="0.00" meanMaxJamLengthInMeters="0.00" maxJamLengthInVehicles="0" maxJamLengthInMeters="0.00" jamLengthInVehiclesSum="0" jamLengthInMetersSum="0.00" meanHaltingDuration="0.00" maxHaltingDuration="0.00" haltingDurationSum="0.00" meanIntervalHaltingDuration="0.00" maxIntervalHaltingDuration="0.00" intervalHaltingDurationSum="0.00" startedHalts="0.00" meanVehicleNumber="0.73" maxVehicleNumber="2" />
   <interval begin="1800.00" end="2100.00" id="detA2A3b" sampledSeconds="117.56" nVehEntered="68" nVehLeft="69" nVehSeen="69" meanSpeed="11.03" meanTimeLoss="0.33" meanOccupancy="10.28" maxOccupancy="35.71" meanMaxJamLengthInVehicles="0.00" meanMaxJamLengthInMeters="0.00" maxJamLengthInVehicles="0" maxJamLengthInMeters="0.00" jamLengthInVehiclesSum="0" jamLengthInMetersSum="0.00" meanHaltingDuration="0.00" maxHaltingDuration="0.00" haltingDurationSum="0.00" meanIntervalHaltingDuration="0.00" maxIntervalHaltingDuration="0.00" intervalHaltingDurationSum="0.00" startedHalts="0.00" meanVehicleNumber="0.65" maxVehicleNumber="2" />
   <interval begin="2100.00" end="2400.00" id="detA2A3b" sampledSeconds="182.08" nVehEntered="59" nVehLeft="58" nVehSeen="59" meanSpeed="6.08" meanTimeLoss="1.72" meanOccupancy="16.82" maxOccupancy="71.43" meanMaxJamLengthInVehicles="0.16" meanMaxJamLengthInMeters="0.77" maxJamLengthInVehicles="2" maxJamLengthInMeters="12.36" jamLengthInVehiclesSum="48" jamLengthInMetersSum="231.44" meanHaltingDuration="9.00" maxHaltingDuration="14.00" haltingDurationSum="54.00" meanIntervalHaltingDuration="9.00" maxIntervalHaltingDuration="14.00" intervalHaltingDurationSum="54.00" startedHalts="6.00" meanVehicleNumber="0.81" maxVehicleNumber="3" />
   <interval begin="2400.00" end="2700.00" id="detA2A3b" sampledSeconds="165.31" nVehEntered="44" nVehLeft="45" nVehSeen="45" meanSpeed="5.14" meanTimeLoss="2.29" meanOccupancy="14.28" maxOccupancy="67.10" meanMaxJamLengthInVehicles="0.07" meanMaxJamLengthInMeters="0.33" maxJamLengthInVehicles="2" maxJamLengthInMeters="11.82" jamLengthInVehiclesSum="20" jamLengthInMetersSum="99.78" meanHaltingDuration="3.86" maxHaltingDuration="8.00" haltingDurationSum="27.00" meanIntervalHaltingDuration="3.86" maxIntervalHaltingDuration="8.00" intervalHaltingDurationSum="27.00" startedHalts="8.00" meanVehicleNumber="0.68" maxVehicleNumber="3" />
   <interval begin="2700.00" end="3000.00" id="detA2A3b" sampledSeconds="15.33" nVehEntered="9" nVehLeft="9" nVehSeen="9" meanSpeed="11.16" meanTimeLoss="0.27" meanOccupancy="1.38" maxOccupancy="35.71" meanMaxJamLengthInVehicles="0.00" meanMaxJamLengthInMeters="0.00" maxJamLengthInVehicles="0" maxJamLengthInMeters="0.00" jamLengthInVehiclesSum="0" jamLengthInMetersSum="0.00" meanHaltingDuration="0.00" maxHaltingDuration="0.00" haltingDurationSum="0.00" meanIntervalHaltingDuration="0.00" maxIntervalHaltingDuration="0.00" intervalHaltingDurationSum="0.00" startedHalts="0.00" meanVehicleNumber="0.08" maxVehicleNumber="2" />
   <interval begin="3000.00" end="3300.00" id="detA2A3b" sampledSeconds="10.61" nVehEntered="6" nVehLeft="6" nVehSeen="6" meanSpeed="10.75" meanTimeLoss="0.38" meanOccupancy="0.85" maxOccupancy="35.71" meanMaxJamLengthInVehicles="0.00" meanMaxJamLengthInMeters="0.00" maxJamLengthInVehicles="0" maxJamLengthInMeters="0.00" jamLengthInVehiclesSum="0" jamLengthInMetersSum="0.00" meanHaltingDuration="0.00" maxHaltingDuration="0.00" haltingDurationSum="0.00" meanIntervalHaltingDuration="0.00" maxIntervalHaltingDuration="0.00" intervalHaltingDurationSum="0.00" startedHalts="0.00" meanVehicleNumber="0.05" maxVehicleNumber="1" />
   <interval begin="3300.00" end="3600.00" id="detA2A3b" sampledSeconds="19.72" nVehEntered="11" nVehLeft="11" nVehSeen="11" meanSpeed="10.60" meanTimeLoss="0.32" meanOccupancy="1.82" maxOccupancy="35.71" meanMaxJamLengthInVehicles="0.00" meanMaxJamLengthInMeters="0.00" maxJamLengthInVehicles="0" maxJamLengthInMeters="0.00" jamLengthInVehiclesSum="0" jamLengthInMetersSum="0.00" meanHaltingDuration="0.00" maxHaltingDuration="0.00" haltingDurationSum="0.00" meanIntervalHaltingDuration="0.00" maxIntervalHaltingDuration="0.00" intervalHaltingDurationSum="0.00" startedHalts="0.00" meanVehicleNumber="0.11" maxVehicleNumber="1" />
   <interval begin="3600.00" end="3900.00" id="detA2A3b" sampledSeconds="30.02" nVehEntered="18" nVehLeft="18" nVehSeen="18" meanSpeed="11.39" meanTimeLoss="0.32" meanOccupancy="2.66" maxOccupancy="35.71" meanMaxJamLengthInVehicles="0.00" meanMaxJamLengthInMeters="0.00" maxJamLengthInVehicles="0" maxJamLengthInMeters="0.00" jamLengthInVehiclesSum="0" jamLengthInMetersSum="0.00" meanHaltingDuration="0.00" maxHaltingDuration="0.00" haltingDurationSum="0.00" meanIntervalHaltingDuration="0.00" maxIntervalHaltingDuration="0.00" intervalHaltingDurationSum="0.00" startedHalts="0.00" meanVehicleNumber="0.16" maxVehicleNumber="2" />
   <interval begin="3900.00" end="4031.00" id="detA2A3b" sampledSeconds="0.00" nVehEntered="0" nVehLeft="0" nVehSeen="0" meanSpeed="-1.00" meanTimeLoss="-1.00" meanOccupancy="0.00" maxOccupancy="0.00" meanMaxJamLengthInVehicles="0.00" meanMaxJamLengthInMeters="0.00" maxJamLengthInVehicles="0" maxJamLengthInMeters="0.00" jamLengthInVehiclesSum="0" jamLengthInMetersSum="0.00" meanHaltingDuration="0.00" maxHaltingDuration="0.00" haltingDurationSum="0.00" meanIntervalHaltingDuration="0.00" maxIntervalHaltingDuration="0.00" intervalHaltingDurationSum="0.00" startedHalts="0.00" meanVehicleNumber="0.00" maxVehicleNumber="0" />
</detector>
