<?xml version="1.0" encoding="UTF-8"?>

<!-- generated on 2021-12-21 20:01:26 by Eclipse SUMO sumo Version 1.10.0
<configuration xmlns:xsi="http://www.w3.org/2001/XMLSchema-instance" xsi:noNamespaceSchemaLocation="http://sumo.dlr.de/xsd/sumoConfiguration.xsd">

    <input>
        <net-file value="C:\Users\Marcus\Desktop\Hauptordner\Studium\Masterstudium\3.%20Semester\Projekt_Sim-Opt\Traffic_Simulation\2X3GridNetwork\2x3net.net.xml"/>
        <route-files value="C:\Users\Marcus\Desktop\Hauptordner\Studium\Masterstudium\3.%20Semester\Projekt_Sim-Opt\Traffic_Simulation\2X3GridNetwork\2x3Routes.xml"/>
        <additional-files value="C:\Users\Marcus\Desktop\Hauptordner\Studium\Masterstudium\3.%20Semester\Projekt_Sim-Opt\Traffic_Simulation\2X3GridNetwork\additionals.xml"/>
    </input>

    <output>
        <tripinfo-output value="tripinfo.xml"/>
        <statistic-output value="statistics.xml"/>
    </output>

    <report>
        <no-step-log value="true"/>
    </report>

    <traci_server>
        <remote-port value="56884"/>
    </traci_server>

</configuration>
-->

<detector xmlns:xsi="http://www.w3.org/2001/XMLSchema-instance" xsi:noNamespaceSchemaLocation="http://sumo.dlr.de/xsd/det_e2_file.xsd">
   <interval begin="0.00" end="300.00" id="detB2B3e" sampledSeconds="70.40" nVehEntered="20" nVehLeft="20" nVehSeen="20" meanSpeed="5.40" meanTimeLoss="2.15" meanOccupancy="7.06" maxOccupancy="71.43" meanMaxJamLengthInVehicles="0.07" meanMaxJamLengthInMeters="0.43" maxJamLengthInVehicles="2" maxJamLengthInMeters="12.58" jamLengthInVehiclesSum="22" jamLengthInMetersSum="127.63" meanHaltingDuration="6.50" maxHaltingDuration="10.00" haltingDurationSum="26.00" meanIntervalHaltingDuration="6.50" maxIntervalHaltingDuration="10.00" intervalHaltingDurationSum="26.00" startedHalts="4.00" meanVehicleNumber="0.30" maxVehicleNumber="2" />
   <interval begin="300.00" end="600.00" id="detB2B3e" sampledSeconds="120.66" nVehEntered="48" nVehLeft="48" nVehSeen="48" meanSpeed="7.56" meanTimeLoss="1.15" meanOccupancy="11.74" maxOccupancy="71.43" meanMaxJamLengthInVehicles="0.08" meanMaxJamLengthInMeters="0.44" maxJamLengthInVehicles="2" maxJamLengthInMeters="12.60" jamLengthInVehiclesSum="24" jamLengthInMetersSum="132.28" meanHaltingDuration="5.80" maxHaltingDuration="7.00" haltingDurationSum="29.00" meanIntervalHaltingDuration="5.80" maxIntervalHaltingDuration="7.00" intervalHaltingDurationSum="29.00" startedHalts="5.00" meanVehicleNumber="0.58" maxVehicleNumber="2" />
   <interval begin="600.00" end="900.00" id="detB2B3e" sampledSeconds="165.30" nVehEntered="52" nVehLeft="51" nVehSeen="52" meanSpeed="5.98" meanTimeLoss="1.83" meanOccupancy="16.29" maxOccupancy="71.43" meanMaxJamLengthInVehicles="0.15" meanMaxJamLengthInMeters="0.91" maxJamLengthInVehicles="2" maxJamLengthInMeters="13.50" jamLengthInVehiclesSum="46" jamLengthInMetersSum="273.86" meanHaltingDuration="6.75" maxHaltingDuration="9.00" haltingDurationSum="54.00" meanIntervalHaltingDuration="6.75" maxIntervalHaltingDuration="9.00" intervalHaltingDurationSum="54.00" startedHalts="8.00" meanVehicleNumber="0.73" maxVehicleNumber="2" />
   <interval begin="900.00" end="1200.00" id="detB2B3e" sampledSeconds="219.53" nVehEntered="57" nVehLeft="58" nVehSeen="58" meanSpeed="4.93" meanTimeLoss="2.43" meanOccupancy="22.49" maxOccupancy="71.43" meanMaxJamLengthInVehicles="0.25" meanMaxJamLengthInMeters="1.52" maxJamLengthInVehicles="2" maxJamLengthInMeters="12.70" jamLengthInVehiclesSum="76" jamLengthInMetersSum="455.59" meanHaltingDuration="8.60" maxHaltingDuration="10.00" haltingDurationSum="86.00" meanIntervalHaltingDuration="8.60" maxIntervalHaltingDuration="10.00" intervalHaltingDurationSum="86.00" startedHalts="10.00" meanVehicleNumber="0.94" maxVehicleNumber="2" />
   <interval begin="1200.00" end="1500.00" id="detB2B3e" sampledSeconds="495.53" nVehEntered="16" nVehLeft="14" nVehSeen="16" meanSpeed="0.57" meanTimeLoss="29.59" meanOccupancy="57.43" maxOccupancy="71.43" meanMaxJamLengthInVehicles="1.41" meanMaxJamLengthInMeters="8.58" maxJamLengthInVehicles="2" maxJamLengthInMeters="12.63" jamLengthInVehiclesSum="422" jamLengthInMetersSum="2573.23" meanHaltingDuration="36.17" maxHaltingDuration="52.00" haltingDurationSum="434.00" meanIntervalHaltingDuration="36.17" maxIntervalHaltingDuration="52.00" intervalHaltingDurationSum="434.00" startedHalts="12.00" meanVehicleNumber="1.70" maxVehicleNumber="2" />
   <interval begin="1500.00" end="1800.00" id="detB2B3e" sampledSeconds="486.81" nVehEntered="12" nVehLeft="12" nVehSeen="14" meanSpeed="0.47" meanTimeLoss="33.59" meanOccupancy="56.51" maxOccupancy="71.43" meanMaxJamLengthInVehicles="1.43" meanMaxJamLengthInMeters="8.75" maxJamLengthInVehicles="2" maxJamLengthInMeters="12.57" jamLengthInVehiclesSum="429" jamLengthInMetersSum="2625.38" meanHaltingDuration="46.82" maxHaltingDuration="53.00" haltingDurationSum="515.00" meanIntervalHaltingDuration="39.82" maxIntervalHaltingDuration="53.00" intervalHaltingDurationSum="438.00" startedHalts="9.00" meanVehicleNumber="1.67" maxVehicleNumber="2" />
   <interval begin="1800.00" end="2100.00" id="detB2B3e" sampledSeconds="268.61" nVehEntered="6" nVehLeft="8" nVehSeen="8" meanSpeed="0.50" meanTimeLoss="32.34" meanOccupancy="31.09" maxOccupancy="71.43" meanMaxJamLengthInVehicles="0.78" meanMaxJamLengthInMeters="4.81" maxJamLengthInVehicles="2" maxJamLengthInMeters="13.50" jamLengthInVehiclesSum="234" jamLengthInMetersSum="1444.18" meanHaltingDuration="39.50" maxHaltingDuration="48.00" haltingDurationSum="316.00" meanIntervalHaltingDuration="30.00" maxIntervalHaltingDuration="48.00" intervalHaltingDurationSum="240.00" startedHalts="6.00" meanVehicleNumber="0.92" maxVehicleNumber="2" />
   <interval begin="2100.00" end="2400.00" id="detB2B3e" sampledSeconds="262.44" nVehEntered="6" nVehLeft="6" nVehSeen="6" meanSpeed="0.43" meanTimeLoss="42.41" meanOccupancy="30.70" maxOccupancy="71.43" meanMaxJamLengthInVehicles="0.77" meanMaxJamLengthInMeters="4.43" maxJamLengthInVehicles="2" maxJamLengthInMeters="12.56" jamLengthInVehiclesSum="231" jamLengthInMetersSum="1327.69" meanHaltingDuration="39.50" maxHaltingDuration="48.00" haltingDurationSum="237.00" meanIntervalHaltingDuration="39.50" maxIntervalHaltingDuration="48.00" intervalHaltingDurationSum="237.00" startedHalts="6.00" meanVehicleNumber="0.90" maxVehicleNumber="2" />
   <interval begin="2400.00" end="2700.00" id="detB2B3e" sampledSeconds="71.10" nVehEntered="24" nVehLeft="24" nVehSeen="24" meanSpeed="6.41" meanTimeLoss="1.62" meanOccupancy="7.17" maxOccupancy="71.43" meanMaxJamLengthInVehicles="0.07" meanMaxJamLengthInMeters="0.42" maxJamLengthInVehicles="2" maxJamLengthInMeters="12.55" jamLengthInVehiclesSum="22" jamLengthInMetersSum="125.08" meanHaltingDuration="8.33" maxHaltingDuration="9.00" haltingDurationSum="25.00" meanIntervalHaltingDuration="8.33" maxIntervalHaltingDuration="9.00" intervalHaltingDurationSum="25.00" startedHalts="3.00" meanVehicleNumber="0.33" maxVehicleNumber="2" />
   <interval begin="2700.00" end="3000.00" id="detB2B3e" sampledSeconds="161.55" nVehEntered="58" nVehLeft="57" nVehSeen="58" meanSpeed="6.81" meanTimeLoss="1.44" meanOccupancy="15.62" maxOccupancy="71.43" meanMaxJamLengthInVehicles="0.13" meanMaxJamLengthInMeters="0.78" maxJamLengthInVehicles="2" maxJamLengthInMeters="12.66" jamLengthInVehiclesSum="39" jamLengthInMetersSum="232.90" meanHaltingDuration="6.57" maxHaltingDuration="11.00" haltingDurationSum="46.00" meanIntervalHaltingDuration="6.57" maxIntervalHaltingDuration="11.00" intervalHaltingDurationSum="46.00" startedHalts="7.00" meanVehicleNumber="0.73" maxVehicleNumber="2" />
   <interval begin="3000.00" end="3300.00" id="detB2B3e" sampledSeconds="127.44" nVehEntered="45" nVehLeft="46" nVehSeen="46" meanSpeed="6.73" meanTimeLoss="1.40" meanOccupancy="12.62" maxOccupancy="71.43" meanMaxJamLengthInVehicles="0.11" meanMaxJamLengthInMeters="0.63" maxJamLengthInVehicles="2" maxJamLengthInMeters="12.52" jamLengthInVehiclesSum="33" jamLengthInMetersSum="190.04" meanHaltingDuration="7.60" maxHaltingDuration="9.00" haltingDurationSum="38.00" meanIntervalHaltingDuration="7.60" maxIntervalHaltingDuration="9.00" intervalHaltingDurationSum="38.00" startedHalts="5.00" meanVehicleNumber="0.58" maxVehicleNumber="2" />
   <interval begin="3300.00" end="3600.00" id="detB2B3e" sampledSeconds="166.58" nVehEntered="48" nVehLeft="48" nVehSeen="48" meanSpeed="5.47" meanTimeLoss="2.10" meanOccupancy="16.70" maxOccupancy="71.43" meanMaxJamLengthInVehicles="0.18" meanMaxJamLengthInMeters="1.08" maxJamLengthInVehicles="2" maxJamLengthInMeters="12.63" jamLengthInVehiclesSum="54" jamLengthInMetersSum="322.73" meanHaltingDuration="8.71" maxHaltingDuration="11.00" haltingDurationSum="61.00" meanIntervalHaltingDuration="8.71" maxIntervalHaltingDuration="11.00" intervalHaltingDurationSum="61.00" startedHalts="7.00" meanVehicleNumber="0.73" maxVehicleNumber="2" />
   <interval begin="3600.00" end="3883.00" id="detB2B3e" sampledSeconds="29.40" nVehEntered="19" nVehLeft="19" nVehSeen="19" meanSpeed="12.28" meanTimeLoss="0.20" meanOccupancy="2.94" maxOccupancy="35.71" meanMaxJamLengthInVehicles="0.00" meanMaxJamLengthInMeters="0.00" maxJamLengthInVehicles="0" maxJamLengthInMeters="0.00" jamLengthInVehiclesSum="0" jamLengthInMetersSum="0.00" meanHaltingDuration="0.00" maxHaltingDuration="0.00" haltingDurationSum="0.00" meanIntervalHaltingDuration="0.00" maxIntervalHaltingDuration="0.00" intervalHaltingDurationSum="0.00" startedHalts="0.00" meanVehicleNumber="0.17" maxVehicleNumber="2" />
</detector>
