<?xml version="1.0" encoding="UTF-8"?>

<!-- generated on 2021-12-14 11:57:46 by Eclipse SUMO sumo Version 1.10.0
<configuration xmlns:xsi="http://www.w3.org/2001/XMLSchema-instance" xsi:noNamespaceSchemaLocation="http://sumo.dlr.de/xsd/sumoConfiguration.xsd">

    <input>
        <net-file value="C:\Users\Marcus\Desktop\Hauptordner\Studium\Masterstudium\3.%20Semester\Projekt_Sim-Opt\Traffic_Simulation\2X3GridNetwork\2x3net.net.xml"/>
        <route-files value="C:\Users\Marcus\Desktop\Hauptordner\Studium\Masterstudium\3.%20Semester\Projekt_Sim-Opt\Traffic_Simulation\2X3GridNetwork\2x3Routes.xml"/>
        <additional-files value="C:\Users\Marcus\Desktop\Hauptordner\Studium\Masterstudium\3.%20Semester\Projekt_Sim-Opt\Traffic_Simulation\2X3GridNetwork\additionals.xml"/>
    </input>

    <output>
        <tripinfo-output value="tripinfo.xml"/>
        <statistic-output value="statistics.xml"/>
    </output>

    <report>
        <no-step-log value="true"/>
    </report>

    <traci_server>
        <remote-port value="56092"/>
    </traci_server>

</configuration>
-->

<detector xmlns:xsi="http://www.w3.org/2001/XMLSchema-instance" xsi:noNamespaceSchemaLocation="http://sumo.dlr.de/xsd/det_e2_file.xsd">
   <interval begin="0.00" end="300.00" id="detA2A3b" sampledSeconds="1.46" nVehEntered="1" nVehLeft="1" nVehSeen="1" meanSpeed="13.03" meanTimeLoss="0.02" meanOccupancy="0.12" maxOccupancy="35.71" meanMaxJamLengthInVehicles="0.00" meanMaxJamLengthInMeters="0.00" maxJamLengthInVehicles="0" maxJamLengthInMeters="0.00" jamLengthInVehiclesSum="0" jamLengthInMetersSum="0.00" meanHaltingDuration="0.00" maxHaltingDuration="0.00" haltingDurationSum="0.00" meanIntervalHaltingDuration="0.00" maxIntervalHaltingDuration="0.00" intervalHaltingDurationSum="0.00" startedHalts="0.00" meanVehicleNumber="0.01" maxVehicleNumber="1" />
   <interval begin="300.00" end="600.00" id="detA2A3b" sampledSeconds="8.50" nVehEntered="6" nVehLeft="6" nVehSeen="6" meanSpeed="13.42" meanTimeLoss="0.08" meanOccupancy="0.75" maxOccupancy="35.71" meanMaxJamLengthInVehicles="0.00" meanMaxJamLengthInMeters="0.00" maxJamLengthInVehicles="0" maxJamLengthInMeters="0.00" jamLengthInVehiclesSum="0" jamLengthInMetersSum="0.00" meanHaltingDuration="0.00" maxHaltingDuration="0.00" haltingDurationSum="0.00" meanIntervalHaltingDuration="0.00" maxIntervalHaltingDuration="0.00" intervalHaltingDurationSum="0.00" startedHalts="0.00" meanVehicleNumber="0.05" maxVehicleNumber="1" />
   <interval begin="600.00" end="900.00" id="detA2A3b" sampledSeconds="5.89" nVehEntered="4" nVehLeft="4" nVehSeen="4" meanSpeed="12.90" meanTimeLoss="0.06" meanOccupancy="0.50" maxOccupancy="35.71" meanMaxJamLengthInVehicles="0.00" meanMaxJamLengthInMeters="0.00" maxJamLengthInVehicles="0" maxJamLengthInMeters="0.00" jamLengthInVehiclesSum="0" jamLengthInMetersSum="0.00" meanHaltingDuration="0.00" maxHaltingDuration="0.00" haltingDurationSum="0.00" meanIntervalHaltingDuration="0.00" maxIntervalHaltingDuration="0.00" intervalHaltingDurationSum="0.00" startedHalts="0.00" meanVehicleNumber="0.04" maxVehicleNumber="1" />
   <interval begin="900.00" end="1200.00" id="detA2A3b" sampledSeconds="5.90" nVehEntered="4" nVehLeft="4" nVehSeen="4" meanSpeed="12.89" meanTimeLoss="0.06" meanOccupancy="0.53" maxOccupancy="35.71" meanMaxJamLengthInVehicles="0.00" meanMaxJamLengthInMeters="0.00" maxJamLengthInVehicles="0" maxJamLengthInMeters="0.00" jamLengthInVehiclesSum="0" jamLengthInMetersSum="0.00" meanHaltingDuration="0.00" maxHaltingDuration="0.00" haltingDurationSum="0.00" meanIntervalHaltingDuration="0.00" maxIntervalHaltingDuration="0.00" intervalHaltingDurationSum="0.00" startedHalts="0.00" meanVehicleNumber="0.03" maxVehicleNumber="1" />
   <interval begin="1200.00" end="1500.00" id="detA2A3b" sampledSeconds="48.72" nVehEntered="30" nVehLeft="29" nVehSeen="30" meanSpeed="11.47" meanTimeLoss="0.29" meanOccupancy="4.15" maxOccupancy="35.71" meanMaxJamLengthInVehicles="0.00" meanMaxJamLengthInMeters="0.00" maxJamLengthInVehicles="0" maxJamLengthInMeters="0.00" jamLengthInVehiclesSum="0" jamLengthInMetersSum="0.00" meanHaltingDuration="0.00" maxHaltingDuration="0.00" haltingDurationSum="0.00" meanIntervalHaltingDuration="0.00" maxIntervalHaltingDuration="0.00" intervalHaltingDurationSum="0.00" startedHalts="0.00" meanVehicleNumber="0.26" maxVehicleNumber="2" />
   <interval begin="1500.00" end="1800.00" id="detA2A3b" sampledSeconds="80.43" nVehEntered="46" nVehLeft="47" nVehSeen="47" meanSpeed="11.01" meanTimeLoss="0.36" meanOccupancy="6.55" maxOccupancy="35.71" meanMaxJamLengthInVehicles="0.00" meanMaxJamLengthInMeters="0.00" maxJamLengthInVehicles="0" maxJamLengthInMeters="0.00" jamLengthInVehiclesSum="0" jamLengthInMetersSum="0.00" meanHaltingDuration="0.00" maxHaltingDuration="0.00" haltingDurationSum="0.00" meanIntervalHaltingDuration="0.00" maxIntervalHaltingDuration="0.00" intervalHaltingDurationSum="0.00" startedHalts="0.00" meanVehicleNumber="0.42" maxVehicleNumber="2" />
   <interval begin="1800.00" end="2100.00" id="detA2A3b" sampledSeconds="76.38" nVehEntered="46" nVehLeft="45" nVehSeen="46" meanSpeed="11.20" meanTimeLoss="0.31" meanOccupancy="6.85" maxOccupancy="35.71" meanMaxJamLengthInVehicles="0.00" meanMaxJamLengthInMeters="0.00" maxJamLengthInVehicles="0" maxJamLengthInMeters="0.00" jamLengthInVehiclesSum="0" jamLengthInMetersSum="0.00" meanHaltingDuration="0.00" maxHaltingDuration="0.00" haltingDurationSum="0.00" meanIntervalHaltingDuration="0.00" maxIntervalHaltingDuration="0.00" intervalHaltingDurationSum="0.00" startedHalts="0.00" meanVehicleNumber="0.43" maxVehicleNumber="2" />
   <interval begin="2100.00" end="2400.00" id="detA2A3b" sampledSeconds="77.76" nVehEntered="45" nVehLeft="46" nVehSeen="46" meanSpeed="11.23" meanTimeLoss="0.37" meanOccupancy="6.74" maxOccupancy="35.71" meanMaxJamLengthInVehicles="0.00" meanMaxJamLengthInMeters="0.00" maxJamLengthInVehicles="0" maxJamLengthInMeters="0.00" jamLengthInVehiclesSum="0" jamLengthInMetersSum="0.00" meanHaltingDuration="0.00" maxHaltingDuration="0.00" haltingDurationSum="0.00" meanIntervalHaltingDuration="0.00" maxIntervalHaltingDuration="0.00" intervalHaltingDurationSum="0.00" startedHalts="0.00" meanVehicleNumber="0.42" maxVehicleNumber="2" />
   <interval begin="2400.00" end="2700.00" id="detA2A3b" sampledSeconds="27.50" nVehEntered="15" nVehLeft="15" nVehSeen="15" meanSpeed="10.37" meanTimeLoss="0.40" meanOccupancy="2.39" maxOccupancy="35.71" meanMaxJamLengthInVehicles="0.00" meanMaxJamLengthInMeters="0.00" maxJamLengthInVehicles="0" maxJamLengthInMeters="0.00" jamLengthInVehiclesSum="0" jamLengthInMetersSum="0.00" meanHaltingDuration="0.00" maxHaltingDuration="0.00" haltingDurationSum="0.00" meanIntervalHaltingDuration="0.00" maxIntervalHaltingDuration="0.00" intervalHaltingDurationSum="0.00" startedHalts="0.00" meanVehicleNumber="0.13" maxVehicleNumber="2" />
   <interval begin="2700.00" end="3000.00" id="detA2A3b" sampledSeconds="13.77" nVehEntered="8" nVehLeft="8" nVehSeen="8" meanSpeed="11.04" meanTimeLoss="0.31" meanOccupancy="1.16" maxOccupancy="35.71" meanMaxJamLengthInVehicles="0.00" meanMaxJamLengthInMeters="0.00" maxJamLengthInVehicles="0" maxJamLengthInMeters="0.00" jamLengthInVehiclesSum="0" jamLengthInMetersSum="0.00" meanHaltingDuration="0.00" maxHaltingDuration="0.00" haltingDurationSum="0.00" meanIntervalHaltingDuration="0.00" maxIntervalHaltingDuration="0.00" intervalHaltingDurationSum="0.00" startedHalts="0.00" meanVehicleNumber="0.07" maxVehicleNumber="1" />
   <interval begin="3000.00" end="3300.00" id="detA2A3b" sampledSeconds="18.44" nVehEntered="10" nVehLeft="10" nVehSeen="10" meanSpeed="10.31" meanTimeLoss="0.52" meanOccupancy="1.79" maxOccupancy="35.71" meanMaxJamLengthInVehicles="0.00" meanMaxJamLengthInMeters="0.00" maxJamLengthInVehicles="0" maxJamLengthInMeters="0.00" jamLengthInVehiclesSum="0" jamLengthInMetersSum="0.00" meanHaltingDuration="0.00" maxHaltingDuration="0.00" haltingDurationSum="0.00" meanIntervalHaltingDuration="0.00" maxIntervalHaltingDuration="0.00" intervalHaltingDurationSum="0.00" startedHalts="0.00" meanVehicleNumber="0.10" maxVehicleNumber="1" />
   <interval begin="3300.00" end="3600.00" id="detA2A3b" sampledSeconds="7.08" nVehEntered="4" nVehLeft="4" nVehSeen="4" meanSpeed="10.74" meanTimeLoss="0.15" meanOccupancy="0.57" maxOccupancy="35.71" meanMaxJamLengthInVehicles="0.00" meanMaxJamLengthInMeters="0.00" maxJamLengthInVehicles="0" maxJamLengthInMeters="0.00" jamLengthInVehiclesSum="0" jamLengthInMetersSum="0.00" meanHaltingDuration="0.00" maxHaltingDuration="0.00" haltingDurationSum="0.00" meanIntervalHaltingDuration="0.00" maxIntervalHaltingDuration="0.00" intervalHaltingDurationSum="0.00" startedHalts="0.00" meanVehicleNumber="0.04" maxVehicleNumber="1" />
   <interval begin="3600.00" end="3900.00" id="detA2A3b" sampledSeconds="5.00" nVehEntered="3" nVehLeft="3" nVehSeen="3" meanSpeed="11.40" meanTimeLoss="0.38" meanOccupancy="0.45" maxOccupancy="35.71" meanMaxJamLengthInVehicles="0.00" meanMaxJamLengthInMeters="0.00" maxJamLengthInVehicles="0" maxJamLengthInMeters="0.00" jamLengthInVehiclesSum="0" jamLengthInMetersSum="0.00" meanHaltingDuration="0.00" maxHaltingDuration="0.00" haltingDurationSum="0.00" meanIntervalHaltingDuration="0.00" maxIntervalHaltingDuration="0.00" intervalHaltingDurationSum="0.00" startedHalts="0.00" meanVehicleNumber="0.03" maxVehicleNumber="2" />
   <interval begin="3900.00" end="3980.00" id="detA2A3b" sampledSeconds="0.00" nVehEntered="0" nVehLeft="0" nVehSeen="0" meanSpeed="-1.00" meanTimeLoss="-1.00" meanOccupancy="0.00" maxOccupancy="0.00" meanMaxJamLengthInVehicles="0.00" meanMaxJamLengthInMeters="0.00" maxJamLengthInVehicles="0" maxJamLengthInMeters="0.00" jamLengthInVehiclesSum="0" jamLengthInMetersSum="0.00" meanHaltingDuration="0.00" maxHaltingDuration="0.00" haltingDurationSum="0.00" meanIntervalHaltingDuration="0.00" maxIntervalHaltingDuration="0.00" intervalHaltingDurationSum="0.00" startedHalts="0.00" meanVehicleNumber="0.00" maxVehicleNumber="0" />
</detector>
