<?xml version="1.0" encoding="UTF-8"?>

<!-- generated on 2022-01-06 17:35:18 by Eclipse SUMO sumo Version 1.10.0
<configuration xmlns:xsi="http://www.w3.org/2001/XMLSchema-instance" xsi:noNamespaceSchemaLocation="http://sumo.dlr.de/xsd/sumoConfiguration.xsd">

    <input>
        <net-file value="C:\Users\Marcus\Desktop\Hauptordner\Studium\Masterstudium\3.%20Semester\Projekt_Sim-Opt\Traffic_Simulation\2X3GridNetwork\2x3net.net.xml"/>
        <route-files value="C:\Users\Marcus\Desktop\Hauptordner\Studium\Masterstudium\3.%20Semester\Projekt_Sim-Opt\Traffic_Simulation\2X3GridNetwork\2x3Routes.xml"/>
        <additional-files value="C:\Users\Marcus\Desktop\Hauptordner\Studium\Masterstudium\3.%20Semester\Projekt_Sim-Opt\Traffic_Simulation\2X3GridNetwork\additionals.xml"/>
    </input>

    <output>
        <tripinfo-output value="tripinfo.xml"/>
        <statistic-output value="statistics.xml"/>
    </output>

    <report>
        <no-step-log value="true"/>
    </report>

    <traci_server>
        <remote-port value="58849"/>
    </traci_server>

</configuration>
-->

<detector xmlns:xsi="http://www.w3.org/2001/XMLSchema-instance" xsi:noNamespaceSchemaLocation="http://sumo.dlr.de/xsd/det_e2_file.xsd">
   <interval begin="0.00" end="300.00" id="detW2B1e" sampledSeconds="39.83" nVehEntered="6" nVehLeft="6" nVehSeen="6" meanSpeed="2.86" meanTimeLoss="4.74" meanOccupancy="4.35" maxOccupancy="35.71" meanMaxJamLengthInVehicles="0.07" meanMaxJamLengthInMeters="0.35" maxJamLengthInVehicles="1" maxJamLengthInMeters="5.00" jamLengthInVehiclesSum="21" jamLengthInMetersSum="105.00" meanHaltingDuration="11.50" maxHaltingDuration="19.00" haltingDurationSum="23.00" meanIntervalHaltingDuration="11.50" maxIntervalHaltingDuration="19.00" intervalHaltingDurationSum="23.00" startedHalts="2.00" meanVehicleNumber="0.15" maxVehicleNumber="1" />
   <interval begin="300.00" end="600.00" id="detW2B1e" sampledSeconds="45.54" nVehEntered="7" nVehLeft="7" nVehSeen="7" meanSpeed="2.92" meanTimeLoss="4.61" meanOccupancy="4.86" maxOccupancy="35.71" meanMaxJamLengthInVehicles="0.09" meanMaxJamLengthInMeters="0.47" maxJamLengthInVehicles="1" maxJamLengthInMeters="5.00" jamLengthInVehiclesSum="28" jamLengthInMetersSum="140.00" meanHaltingDuration="29.00" maxHaltingDuration="29.00" haltingDurationSum="29.00" meanIntervalHaltingDuration="29.00" maxIntervalHaltingDuration="29.00" intervalHaltingDurationSum="29.00" startedHalts="1.00" meanVehicleNumber="0.17" maxVehicleNumber="1" />
   <interval begin="600.00" end="900.00" id="detW2B1e" sampledSeconds="62.94" nVehEntered="5" nVehLeft="5" nVehSeen="5" meanSpeed="1.51" meanTimeLoss="10.69" meanOccupancy="7.02" maxOccupancy="35.71" meanMaxJamLengthInVehicles="0.13" meanMaxJamLengthInMeters="0.65" maxJamLengthInVehicles="1" maxJamLengthInMeters="5.00" jamLengthInVehiclesSum="39" jamLengthInMetersSum="195.00" meanHaltingDuration="10.75" maxHaltingDuration="20.00" haltingDurationSum="43.00" meanIntervalHaltingDuration="10.75" maxIntervalHaltingDuration="20.00" intervalHaltingDurationSum="43.00" startedHalts="4.00" meanVehicleNumber="0.23" maxVehicleNumber="1" />
   <interval begin="900.00" end="1200.00" id="detW2B1e" sampledSeconds="41.99" nVehEntered="4" nVehLeft="4" nVehSeen="4" meanSpeed="1.81" meanTimeLoss="8.60" meanOccupancy="4.58" maxOccupancy="35.71" meanMaxJamLengthInVehicles="0.09" meanMaxJamLengthInMeters="0.45" maxJamLengthInVehicles="1" maxJamLengthInMeters="5.00" jamLengthInVehiclesSum="27" jamLengthInMetersSum="135.00" meanHaltingDuration="14.50" maxHaltingDuration="18.00" haltingDurationSum="29.00" meanIntervalHaltingDuration="14.50" maxIntervalHaltingDuration="18.00" intervalHaltingDurationSum="29.00" startedHalts="2.00" meanVehicleNumber="0.15" maxVehicleNumber="1" />
   <interval begin="1200.00" end="1500.00" id="detW2B1e" sampledSeconds="25.70" nVehEntered="6" nVehLeft="6" nVehSeen="6" meanSpeed="4.44" meanTimeLoss="2.38" meanOccupancy="2.68" maxOccupancy="35.71" meanMaxJamLengthInVehicles="0.04" meanMaxJamLengthInMeters="0.18" maxJamLengthInVehicles="1" maxJamLengthInMeters="5.00" jamLengthInVehiclesSum="11" jamLengthInMetersSum="55.00" meanHaltingDuration="12.00" maxHaltingDuration="12.00" haltingDurationSum="12.00" meanIntervalHaltingDuration="12.00" maxIntervalHaltingDuration="12.00" intervalHaltingDurationSum="12.00" startedHalts="1.00" meanVehicleNumber="0.10" maxVehicleNumber="1" />
   <interval begin="1500.00" end="1800.00" id="detW2B1e" sampledSeconds="60.86" nVehEntered="8" nVehLeft="8" nVehSeen="8" meanSpeed="2.50" meanTimeLoss="5.71" meanOccupancy="6.66" maxOccupancy="35.71" meanMaxJamLengthInVehicles="0.12" meanMaxJamLengthInMeters="0.58" maxJamLengthInVehicles="1" maxJamLengthInMeters="5.00" jamLengthInVehiclesSum="35" jamLengthInMetersSum="175.00" meanHaltingDuration="12.67" maxHaltingDuration="16.00" haltingDurationSum="38.00" meanIntervalHaltingDuration="12.67" maxIntervalHaltingDuration="16.00" intervalHaltingDurationSum="38.00" startedHalts="3.00" meanVehicleNumber="0.23" maxVehicleNumber="1" />
   <interval begin="1800.00" end="2100.00" id="detW2B1e" sampledSeconds="132.95" nVehEntered="13" nVehLeft="13" nVehSeen="13" meanSpeed="1.86" meanTimeLoss="8.33" meanOccupancy="14.82" maxOccupancy="71.43" meanMaxJamLengthInVehicles="0.30" meanMaxJamLengthInMeters="1.86" maxJamLengthInVehicles="2" maxJamLengthInMeters="12.57" jamLengthInVehiclesSum="91" jamLengthInMetersSum="557.68" meanHaltingDuration="23.75" maxHaltingDuration="25.00" haltingDurationSum="95.00" meanIntervalHaltingDuration="23.75" maxIntervalHaltingDuration="25.00" intervalHaltingDurationSum="95.00" startedHalts="4.00" meanVehicleNumber="0.49" maxVehicleNumber="2" />
   <interval begin="2100.00" end="2400.00" id="detW2B1e" sampledSeconds="42.19" nVehEntered="13" nVehLeft="13" nVehSeen="13" meanSpeed="5.85" meanTimeLoss="1.35" meanOccupancy="4.10" maxOccupancy="35.71" meanMaxJamLengthInVehicles="0.03" meanMaxJamLengthInMeters="0.17" maxJamLengthInVehicles="1" maxJamLengthInMeters="5.00" jamLengthInVehiclesSum="10" jamLengthInMetersSum="50.00" meanHaltingDuration="11.00" maxHaltingDuration="11.00" haltingDurationSum="11.00" meanIntervalHaltingDuration="11.00" maxIntervalHaltingDuration="11.00" intervalHaltingDurationSum="11.00" startedHalts="1.00" meanVehicleNumber="0.19" maxVehicleNumber="1" />
   <interval begin="2400.00" end="2700.00" id="detW2B1e" sampledSeconds="8.18" nVehEntered="4" nVehLeft="4" nVehSeen="4" meanSpeed="9.29" meanTimeLoss="0.15" meanOccupancy="0.72" maxOccupancy="35.71" meanMaxJamLengthInVehicles="0.00" meanMaxJamLengthInMeters="0.00" maxJamLengthInVehicles="0" maxJamLengthInMeters="0.00" jamLengthInVehiclesSum="0" jamLengthInMetersSum="0.00" meanHaltingDuration="0.00" maxHaltingDuration="0.00" haltingDurationSum="0.00" meanIntervalHaltingDuration="0.00" maxIntervalHaltingDuration="0.00" intervalHaltingDurationSum="0.00" startedHalts="0.00" meanVehicleNumber="0.04" maxVehicleNumber="1" />
   <interval begin="2700.00" end="3000.00" id="detW2B1e" sampledSeconds="52.59" nVehEntered="6" nVehLeft="6" nVehSeen="6" meanSpeed="2.17" meanTimeLoss="6.87" meanOccupancy="5.72" maxOccupancy="35.71" meanMaxJamLengthInVehicles="0.11" meanMaxJamLengthInMeters="0.53" maxJamLengthInVehicles="1" maxJamLengthInMeters="5.00" jamLengthInVehiclesSum="32" jamLengthInMetersSum="160.00" meanHaltingDuration="11.67" maxHaltingDuration="13.00" haltingDurationSum="35.00" meanIntervalHaltingDuration="11.67" maxIntervalHaltingDuration="13.00" intervalHaltingDurationSum="35.00" startedHalts="3.00" meanVehicleNumber="0.19" maxVehicleNumber="1" />
   <interval begin="3000.00" end="3300.00" id="detW2B1e" sampledSeconds="16.28" nVehEntered="8" nVehLeft="8" nVehSeen="8" meanSpeed="9.33" meanTimeLoss="0.14" meanOccupancy="1.41" maxOccupancy="35.71" meanMaxJamLengthInVehicles="0.00" meanMaxJamLengthInMeters="0.00" maxJamLengthInVehicles="0" maxJamLengthInMeters="0.00" jamLengthInVehiclesSum="0" jamLengthInMetersSum="0.00" meanHaltingDuration="0.00" maxHaltingDuration="0.00" haltingDurationSum="0.00" meanIntervalHaltingDuration="0.00" maxIntervalHaltingDuration="0.00" intervalHaltingDurationSum="0.00" startedHalts="0.00" meanVehicleNumber="0.08" maxVehicleNumber="1" />
   <interval begin="3300.00" end="3600.00" id="detW2B1e" sampledSeconds="6.21" nVehEntered="3" nVehLeft="3" nVehSeen="3" meanSpeed="9.18" meanTimeLoss="0.17" meanOccupancy="0.54" maxOccupancy="35.71" meanMaxJamLengthInVehicles="0.00" meanMaxJamLengthInMeters="0.00" maxJamLengthInVehicles="0" maxJamLengthInMeters="0.00" jamLengthInVehiclesSum="0" jamLengthInMetersSum="0.00" meanHaltingDuration="0.00" maxHaltingDuration="0.00" haltingDurationSum="0.00" meanIntervalHaltingDuration="0.00" maxIntervalHaltingDuration="0.00" intervalHaltingDurationSum="0.00" startedHalts="0.00" meanVehicleNumber="0.03" maxVehicleNumber="1" />
   <interval begin="3600.00" end="3865.00" id="detW2B1e" sampledSeconds="0.00" nVehEntered="0" nVehLeft="0" nVehSeen="0" meanSpeed="-1.00" meanTimeLoss="-1.00" meanOccupancy="0.00" maxOccupancy="0.00" meanMaxJamLengthInVehicles="0.00" meanMaxJamLengthInMeters="0.00" maxJamLengthInVehicles="0" maxJamLengthInMeters="0.00" jamLengthInVehiclesSum="0" jamLengthInMetersSum="0.00" meanHaltingDuration="0.00" maxHaltingDuration="0.00" haltingDurationSum="0.00" meanIntervalHaltingDuration="0.00" maxIntervalHaltingDuration="0.00" intervalHaltingDurationSum="0.00" startedHalts="0.00" meanVehicleNumber="0.00" maxVehicleNumber="0" />
</detector>
