<?xml version="1.0" encoding="UTF-8"?>

<!-- generated on 2021-11-16 11:28:40 by Eclipse SUMO sumo Version 1.10.0
<configuration xmlns:xsi="http://www.w3.org/2001/XMLSchema-instance" xsi:noNamespaceSchemaLocation="http://sumo.dlr.de/xsd/sumoConfiguration.xsd">

    <input>
        <net-file value="C:\Users\Marcus\Desktop\Hauptordner\Studium\Masterstudium\3.%20Semester\Projekt_Sim-Opt\Traffic_Simulation\TwoCross\twoCross.net.xml"/>
        <route-files value="C:\Users\Marcus\Desktop\Hauptordner\Studium\Masterstudium\3.%20Semester\Projekt_Sim-Opt\Traffic_Simulation\TwoCross\twoCrossRoutes.xml"/>
        <additional-files value="C:\Users\Marcus\Desktop\Hauptordner\Studium\Masterstudium\3.%20Semester\Projekt_Sim-Opt\Traffic_Simulation\TwoCross\additionals.xml"/>
    </input>

    <output>
        <tripinfo-output value="tripinfo.xml"/>
        <statistic-output value="statistics.xml"/>
    </output>

    <report>
        <no-step-log value="true"/>
    </report>

    <traci_server>
        <remote-port value="64199"/>
    </traci_server>

</configuration>
-->

<detector xmlns:xsi="http://www.w3.org/2001/XMLSchema-instance" xsi:noNamespaceSchemaLocation="http://sumo.dlr.de/xsd/det_e1_file.xsd">
    <interval begin="0.00" end="300.00" id="detb3Lb2_0" nVehContrib="56" flow="672.00" occupancy="7.48" speed="12.73" harmonicMeanSpeed="12.47" length="5.00" nVehEntered="56"/>
    <interval begin="300.00" end="600.00" id="detb3Lb2_0" nVehContrib="55" flow="660.00" occupancy="20.91" speed="8.06" harmonicMeanSpeed="4.38" length="5.00" nVehEntered="55"/>
</detector>
